astrochart_svg/__init__.py
astrochart_svg/astrochart_svg.py
astrochart_svg/settings.py
astrochart_svg/template.xml
astrochart_svg-1.0.1.dist-info/METADATA
astrochart_svg-1.0.1.dist-info/WHEEL
astrochart_svg-1.0.1.dist-info/top_level.txt
astrochart_svg-1.0.1.dist-info/RECORD
