Metadata-Version: 2.1
Name: astrochart-svg
Version: 1.0.1
Summary: Chart SVG generator for astrology.
Home-page: https://github.com/g-battaglia/astrochart_svg
Author: Giacomo Battaglia
Author-email: battaglia.giacomo@yahoo.it
License: UNKNOWN
Platform: UNKNOWN
Classifier: Programming Language :: Python :: 3
Classifier: License :: OSI Approved :: MIT License
Classifier: Operating System :: OS Independent
Requires-Python: >=3.6
Requires-Dist: kerykeion
